django_yearlessdate-1.3.dist-info/METADATA
django_yearlessdate-1.3.dist-info/RECORD
django_yearlessdate-1.3.dist-info/WHEEL
django_yearlessdate-1.3.dist-info/top_level.txt
djangoyearlessdate/__init__.py
djangoyearlessdate/forms.py
djangoyearlessdate/helpers.py
djangoyearlessdate/models.py
