Metadata-Version: 2.1
Name: django-yearlessdate
Version: 1.3
Summary: Django field for storing dates without years.
Home-page: http://github.com/seddonym/django-yearlessdate/
Author: David Seddon
Author-email: david@seddonym.me
License: BSD
Keywords: django date yearlessdate
Platform: any
Classifier: Development Status :: 5 - Production/Stable
Classifier: License :: OSI Approved :: BSD License
Classifier: Programming Language :: Python
Classifier: Framework :: Django
Classifier: Programming Language :: Python :: 2
Classifier: Programming Language :: Python :: 2.7
Classifier: Programming Language :: Python :: 3
Classifier: Programming Language :: Python :: 3.6
Classifier: Framework :: Django :: 1.8
Classifier: Framework :: Django :: 1.9
Classifier: Framework :: Django :: 1.10
Classifier: Framework :: Django :: 1.11
Classifier: Framework :: Django :: 2.0
Classifier: Operating System :: OS Independent
